Metadata-Version: 2.1
Name: odoo10-addon-document-page-procedure
Version: 10.0.1.1.0
Summary: Document Management - Wiki - Procedures
Home-page: http://www.savoirfairelinux.com
Author: Savoir-faire Linux,Odoo Community Association (OCA)
Author-email: support@odoo-community.org
License: AGPL-3
Platform: UNKNOWN
Classifier: Programming Language :: Python
Classifier: Framework :: Odoo
Classifier: License :: OSI Approved :: GNU Affero General Public License v3
Requires-Python: ~=2.7
Requires-Dist: odoo10-addon-document-page-work-instruction
Requires-Dist: odoo (<10.1dev,>=10.0)
